{
  "santos": [
    {
      "nombre": "Shiryus",
      "constelacion": "Dragon",
      "id": 2
    },
    {
      "id": 3,
      "nombre": "Hyoga",
      "constelacion": "Cisne"
    },
    {
      "id": 4
    }
  ],
  "dioses": [
    {
      "id": 1,
      "nombre": "Athena",
      "de": "Tierra"
    },
    {
      "id": 2,
      "nombre": "Poseidón",
      "de": "Mar"
    },
    {
      "id": 3,
      "nombre": "Hades",
      "de": "Inframundo"
    },
    {
      "id": 4,
      "nombre": "Zeus",
      "de": "Cielo"
    }
  ]
}